[
  {
    "host-name": "Edge1",
    "deviceIP": "10.0.0.1",
    "local-system-ip": "10.0.0.1",
    "site-id": "1",
    "device-groups": [
      "No groups"
    ],
    "uuid": "C8K-3D1A8960-6E76-532C-DA93-50626FC5797E",
    "personality": "vedge",
    "configCloudxMode": "none"
  },
  {
    "host-name": "Edge2",
    "deviceIP": "10.0.0.2",
    "local-system-ip": "10.0.0.2",
    "site-id": "2",
    "device-groups": [
      "No groups"
    ],
    "uuid": "C8K-D4CE7174-5261-7E6F-91EA-4926BCF4C2DD",
    "personality": "vedge",
    "configCloudxMode": "none"
  }
]